README.md
setup.py
pybeepbeep/__init__.py
pybeepbeep/ranging.py
pybeepbeep.egg-info/PKG-INFO
pybeepbeep.egg-info/SOURCES.txt
pybeepbeep.egg-info/dependency_links.txt
pybeepbeep.egg-info/requires.txt
pybeepbeep.egg-info/top_level.txt