Metadata-Version: 2.1
Name: pybeepbeep
Version: 0.0.0
Summary: pybeepbeep is a python implementation of the BeepBeep cooperative ranging algorithm.
Home-page: https://github.com/LumineerLabs/pybeepbeep
Author: Lane Haury
Author-email: lane@lumineerlabs.com
License: UNKNOWN
Platform: UNKNOWN
Classifier: License :: OSI Approved :: MIT License
Classifier: Programming Language :: Python
Classifier: Operating System :: OS Independent
